baywatch/__init__.py
baywatch/app.py
baywatch/bay.py
baywatch/config_control.py
baywatch/version.py
baywatch/data/categories.json
baywatch/data/categories_short.json
baywatch/data/conf.json
baywatch/data/mirrors.txt
baywatch/data/trackers.txt
bay_watch-0.1.8.dist-info/METADATA
bay_watch-0.1.8.dist-info/WHEEL
bay_watch-0.1.8.dist-info/entry_points.txt
bay_watch-0.1.8.dist-info/top_level.txt
bay_watch-0.1.8.dist-info/RECORD
