Metadata-Version: 2.1
Name: bay-watch
Version: 0.1.8
Summary: TUI for TPB + Peerflix + Transmission
Author-email: Hudson Bailey <hudsondiggsbailey@gmail.com>
License: MIT License
Project-URL: Homepage, https://github.com/hdb/baywatch
Project-URL: Bug Tracker, https://github.com/hdb/baywatch/issues
Classifier: Programming Language :: Python :: 3
Classifier: License :: OSI Approved :: MIT License
Classifier: Operating System :: OS Independent
Classifier: Topic :: Communications :: File Sharing
Requires-Python: >=3.7
Requires-Dist: requests >=2.27.1
Requires-Dist: textual ~=0.1.17
Requires-Dist: textual-inputs ~=0.2.5
Requires-Dist: ck-widgets ~=0.2.0
Requires-Dist: pyfiglet ~=0.8.post1
Requires-Dist: transmission-rpc ~=3.3.0
Requires-Dist: pyperclip ~=1.8.2
